pyexifwrangle/__init__.py
pyexifwrangle/wrangle.py
pyexifwrangle-0.2.1.dist-info/METADATA
pyexifwrangle-0.2.1.dist-info/WHEEL
pyexifwrangle-0.2.1.dist-info/top_level.txt
pyexifwrangle-0.2.1.dist-info/RECORD
