Metadata-Version: 2.1
Name: pyexifwrangle
Version: 0.2.1
Summary: A Python package for wrangling EXIF data extracted from images using Phil Harvey's EXIFTool.
Author-email: Stephanie Reinders <reinders.stephanie@gmail.com>
Project-URL: Homepage, https://github.com/CSAFE-ISU/pyexifwrangle
Project-URL: Bug Tracker, https://github.com/CSAFE-ISU/pyexifwrangle/issues
Classifier: Programming Language :: Python :: 3
Classifier: License :: OSI Approved :: MIT License
Classifier: Operating System :: OS Independent
Requires-Python: >=3.7
